pyscrapers/__init__.py
pyscrapers/configs.py
pyscrapers/main.py
pyscrapers/static.py
pyscrapers/utils.py
pyscrapers/core/__init__.py
pyscrapers/core/cookies.py
pyscrapers/core/ext_lxml.py
pyscrapers/core/ext_requests.py
pyscrapers/core/ffprobe.py
pyscrapers/core/json.py
pyscrapers/core/url_set.py
pyscrapers/core/utils.py
pyscrapers/workers/__init__.py
pyscrapers/workers/audible.py
pyscrapers/workers/drumeo.py
pyscrapers/workers/facebook.py
pyscrapers/workers/getpocket.py
pyscrapers/workers/instagram.py
pyscrapers/workers/instagram_stories.py
pyscrapers/workers/mamba_ru.py
pyscrapers/workers/netflix.py
pyscrapers/workers/pornhub.py
pyscrapers/workers/sxyprn.py
pyscrapers/workers/travelgirls.py
pyscrapers/workers/vk.py
pyscrapers/workers/youtube_dl_handlers.py
pyscrapers-0.0.67.dist-info/LICENSE
pyscrapers-0.0.67.dist-info/METADATA
pyscrapers-0.0.67.dist-info/WHEEL
pyscrapers-0.0.67.dist-info/entry_points.txt
pyscrapers-0.0.67.dist-info/top_level.txt
pyscrapers-0.0.67.dist-info/RECORD
