Metadata-Version: 2.1
Name: pyscrapers
Version: 0.0.67
Summary: project to produce various useful scrapers
Home-page: https://veltzer.github.io/pyscrapers
Download-URL: https://github.com/veltzer/pyscrapers
Author: Mark Veltzer
Author-email: mark.veltzer@gmail.com
Maintainer: Mark Veltzer
Maintainer-email: mark.veltzer@gmail.com
License: MIT
Keywords: scrape,images,social,facebook,instagram,vk,download,pics
Platform: python3
Classifier: Development Status :: 4 - Beta
Classifier: Environment :: Console
Classifier: Operating System :: OS Independent
Classifier: Programming Language :: Python
Classifier: Programming Language :: Python :: 3
Classifier: Programming Language :: Python :: 3 :: Only
Classifier: Programming Language :: Python :: 3.11
Classifier: Topic :: Utilities
Classifier: License :: OSI Approved :: MIT License
License-File: LICENSE
Requires-Dist: lxml
Requires-Dist: requests
Requires-Dist: browser-cookie3
Requires-Dist: dbus-python
Requires-Dist: pytconf
Requires-Dist: pylogconf
Requires-Dist: pornhub-api
Requires-Dist: youtube-dl
Requires-Dist: pyeventroute
Requires-Dist: fake-useragent
Requires-Dist: tqdm
Requires-Dist: beautifulsoup4
Requires-Dist: pydantic==1.10.13
